{
  "id": "785e693c-e1fc-45fe-93f0-119eddb6d6c7",
  "name": "Corton-Charlemagne Grand Cru",
  "full-name": "Philippe Pacalet Corton-Charlemagne Grand Cru 2011",
  "producer": {
    "id": "17e5f004-4286-4762-861a-8c029331e982",
    "name": "Philippe Pacalet"
  },
  "vintage": "2011",
  "base-vintage": null,
  "degorgee": null,
  "sur-lie": null,
  "colour": "white",
  "carbonation": "still",
  "sweetness": "dry",
  "country": {
    "id": "c6c8738e-3780-44b1-9e8c-d2fff16ed206",
    "name": "France"
  },
  "grapes": [
    {
      "id": "347c3f7d-0c6c-469d-a2d1-a96b45d03d93",
      "name": "Chardonnay"
    }
  ],
  "alcohol": "13",
  "sugar": "NA",
  "prices": [
    "13500 UAH"
  ],
  "available": 0.0,
  "image": "images/78/5e693c-e1fc-45fe-93f0-119eddb6d6c7/2023-10-13-08-48-22-IMG-9808.webp",
  "rating": "8.6"
}
